countdown_numbers_solver/__init__.py
countdown_numbers_solver-1.0.0.dist-info/LICENSE
countdown_numbers_solver-1.0.0.dist-info/METADATA
countdown_numbers_solver-1.0.0.dist-info/WHEEL
countdown_numbers_solver-1.0.0.dist-info/top_level.txt
countdown_numbers_solver-1.0.0.dist-info/RECORD
