Metadata-Version: 2.1
Name: countdown-numbers-solver
Version: 1.0.0
Summary: Python function for solving the numbers game problems in the British game show Countdown.
Home-page: https://github.com/exitexit/countdown-numbers-solver
Author: Tao Xie
Author-email: taoxie@alumni.unc.edu
License: UNKNOWN
Platform: UNKNOWN
Classifier: Programming Language :: Python :: 3
Classifier: License :: OSI Approved :: Apache Software License
Classifier: Operating System :: OS Independent
Requires-Python: >=3.6
